PyDBL/__init__.py
PyDBL-1.4.dist-info/METADATA
PyDBL-1.4.dist-info/WHEEL
PyDBL-1.4.dist-info/top_level.txt
PyDBL-1.4.dist-info/RECORD
